x509middleware
