Metadata-Version: 2.1
Name: x509middleware
Version: 1.1
Summary: Python middleware for working with (client) certificates.
Home-page: https://github.com/wagnerflo/x509middleware
Author: Florian Wagner
Author-email: florian@wagner-flo.net
License: UNKNOWN
Platform: UNKNOWN
Classifier: Development Status :: 4 - Beta
Classifier: Environment :: Web Environment
Classifier: Intended Audience :: Developers
Classifier: License :: OSI Approved :: Apache Software License
Classifier: Programming Language :: Python :: 3 :: Only
Classifier: Topic :: Software Development :: Libraries :: Python Modules
Requires-Python: >=3.3
